onegov.winterthur-0.7.5-py3.6-nspkg.pth
onegov/winterthur/.gitignore
onegov/winterthur/__init__.py
onegov/winterthur/app.py
onegov/winterthur/cli.py
onegov/winterthur/cronjobs.py
onegov/winterthur/daycare.py
onegov/winterthur/directory_search_widgets.py
onegov/winterthur/initial_content.py
onegov/winterthur/layout.py
onegov/winterthur/path.py
onegov/winterthur/roadwork.py
onegov/winterthur/translations.py
onegov/winterthur/upgrade.py
onegov/winterthur/assets/js/iframe-enhancements.js
onegov/winterthur/assets/js/iframe-resizer-contentwindow.js
onegov/winterthur/assets/js/iframe-resizer-options.js
onegov/winterthur/assets/js/street-search.js
onegov/winterthur/assets/js/string-score.js
onegov/winterthur/assets/js/wade.js
onegov/winterthur/assets/js/winterthur.js
onegov/winterthur/collections/__init__.py
onegov/winterthur/collections/address.py
onegov/winterthur/collections/mission_report.py
onegov/winterthur/content/de.yaml
onegov/winterthur/forms/__init__.py
onegov/winterthur/forms/mission_report.py
onegov/winterthur/locale/de_CH/LC_MESSAGES/onegov.winterthur.po
onegov/winterthur/models/__init__.py
onegov/winterthur/models/address.py
onegov/winterthur/models/extensions.py
onegov/winterthur/models/mission_report.py
onegov/winterthur/static/civil-defence.svg
onegov/winterthur/templates/daycare.pt
onegov/winterthur/templates/macros.pt
onegov/winterthur/templates/mission_report.pt
onegov/winterthur/templates/mission_report_vehicles.pt
onegov/winterthur/templates/mission_reports.pt
onegov/winterthur/templates/roadwork.pt
onegov/winterthur/templates/roadwork_connection_error.pt
onegov/winterthur/templates/roadworks.pt
onegov/winterthur/templates/street.pt
onegov/winterthur/templates/streets.pt
onegov/winterthur/templates/svg.pt
onegov/winterthur/tests/conftest.py
onegov/winterthur/tests/test_daycare.py
onegov/winterthur/tests/test_models.py
onegov/winterthur/tests/test_views.py
onegov/winterthur/tests/fixtures/addresses.csv
onegov/winterthur/tests/fixtures/streets.csv
onegov.winterthur-0.7.5.dist-info/METADATA
onegov.winterthur-0.7.5.dist-info/WHEEL
onegov.winterthur-0.7.5.dist-info/entry_points.txt
onegov.winterthur-0.7.5.dist-info/namespace_packages.txt
onegov.winterthur-0.7.5.dist-info/top_level.txt
onegov.winterthur-0.7.5.dist-info/RECORD
